filmoptics/__init__.py
filmoptics/main.py
filmoptics/tmm_core.py
filmoptics/tmm_utils.py
filmoptics-0.0.1.dist-info/LICENSE
filmoptics-0.0.1.dist-info/METADATA
filmoptics-0.0.1.dist-info/WHEEL
filmoptics-0.0.1.dist-info/top_level.txt
filmoptics-0.0.1.dist-info/RECORD
